dnachisel/Location.py
dnachisel/__init__.py
dnachisel/version.py
dnachisel/DnaOptimizationProblem/CircularDnaOptimizationProblem.py
dnachisel/DnaOptimizationProblem/DnaOptimizationProblem.py
dnachisel/DnaOptimizationProblem/NoSolutionError.py
dnachisel/DnaOptimizationProblem/__init__.py
dnachisel/DnaOptimizationProblem/mixins/ConstraintsSolverMixin.py
dnachisel/DnaOptimizationProblem/mixins/ObjectivesMaximizerMixin.py
dnachisel/DnaOptimizationProblem/mixins/RecordRepresentationMixin.py
dnachisel/DnaOptimizationProblem/mixins/__init__.py
dnachisel/MutationSpace/MutationChoice.py
dnachisel/MutationSpace/MutationSpace.py
dnachisel/MutationSpace/__init__.py
dnachisel/SequencePattern/DnaNotationPattern.py
dnachisel/SequencePattern/EnzymeSitePattern.py
dnachisel/SequencePattern/HomopolymerPattern.py
dnachisel/SequencePattern/MotifPssmPattern.py
dnachisel/SequencePattern/RepeatedKmerPattern.py
dnachisel/SequencePattern/SequencePattern.py
dnachisel/SequencePattern/__init__.py
dnachisel/Specification/FeatureRepresentationMixin.py
dnachisel/Specification/Specification.py
dnachisel/Specification/SpecificationSet.py
dnachisel/Specification/__init__.py
dnachisel/Specification/SpecEvaluation/ProblemConstraintsEvaluations.py
dnachisel/Specification/SpecEvaluation/ProblemObjectivesEvaluations.py
dnachisel/Specification/SpecEvaluation/SpecEvaluation.py
dnachisel/Specification/SpecEvaluation/SpecEvaluations.py
dnachisel/Specification/SpecEvaluation/__init__.py
dnachisel/biotools/__init__.py
dnachisel/biotools/biotables.py
dnachisel/biotools/blast_sequence.py
dnachisel/biotools/bowtie.py
dnachisel/biotools/enzymes_operations.py
dnachisel/biotools/formatting_operations.py
dnachisel/biotools/gc_content.py
dnachisel/biotools/genbank_operations.py
dnachisel/biotools/indices_operations.py
dnachisel/biotools/random_sequences.py
dnachisel/biotools/sequences_differences.py
dnachisel/biotools/sequences_operations.py
dnachisel/biotools/data/README.md
dnachisel/biotools/data/complements.csv
dnachisel-3.2.14.dist-info/licenses/LICENCE.txt
dnachisel-3.2.14.dist-info/METADATA
dnachisel-3.2.14.dist-info/WHEEL
dnachisel-3.2.14.dist-info/entry_points.txt
dnachisel-3.2.14.dist-info/top_level.txt
dnachisel-3.2.14.dist-info/RECORD
