Metadata-Version: 2.4
Name: dnachisel
Version: 3.2.14
Summary: Optimize DNA sequences under constraints.
Home-page: https://github.com/Edinburgh-Genome-Foundry/DnaChisel
Author: Zulko
License-Expression: MIT
Project-URL: Homepage, https://github.com/Edinburgh-Genome-Foundry/PKG
Keywords: DNA,gene,design,codon,optimization,constraints,synthetic biology
License-File: LICENCE.txt
Requires-Dist: numpy
Requires-Dist: biopython
Requires-Dist: proglog
Requires-Dist: docopt
Requires-Dist: flametree
Requires-Dist: python_codon_tables
Provides-Extra: reports
Requires-Dist: pdf_reports; extra == "reports"
Requires-Dist: sequenticon; extra == "reports"
Requires-Dist: matplotlib; extra == "reports"
Requires-Dist: dna_features_viewer; extra == "reports"
Requires-Dist: pandas; extra == "reports"
Provides-Extra: tests
Requires-Dist: pytest; extra == "tests"
Requires-Dist: pytest-cov; extra == "tests"
Requires-Dist: coveralls; extra == "tests"
Requires-Dist: geneblocks; extra == "tests"
Requires-Dist: genome_collector; extra == "tests"
Requires-Dist: matplotlib; extra == "tests"
Requires-Dist: primer3-py; extra == "tests"
Dynamic: home-page
Dynamic: license-file
